dsptools/__init__.py
dsptools/data_transfer/__init__.py
dsptools/data_transfer/azurestorageblob.py
dsptools/data_transfer/savetosql.py
dsptools/errors/__init__.py
dsptools/errors/data.py
dsptools/errors/execution.py
dsptools/utils/__init__.py
dsptools/utils/execution.py
dsptools/utils/notifications.py
rwhealth_dsptools-0.1.4.dist-info/METADATA
rwhealth_dsptools-0.1.4.dist-info/WHEEL
rwhealth_dsptools-0.1.4.dist-info/top_level.txt
rwhealth_dsptools-0.1.4.dist-info/RECORD
